snowflake_id_generator/__init__.py
snowflake_id_generator/snowflake.py
tests/__init__.py
tests/test_snowflake.py
snowflake_id_generator-1.0.0.dist-info/METADATA
snowflake_id_generator-1.0.0.dist-info/WHEEL
snowflake_id_generator-1.0.0.dist-info/top_level.txt
snowflake_id_generator-1.0.0.dist-info/RECORD
